fasvadms_client/__init__.py
fasvadms_client/api_client.py
fasvadms_client/configuration.py
fasvadms_client/rest.py
fasvadms_client/api/__init__.py
fasvadms_client/api/drive_api.py
fasvadms_client/api/scene_api.py
fasvadms_client/api/sensor_api.py
fasvadms_client/api/signal_api.py
fasvadms_client/api/signal_type_api.py
fasvadms_client/api/thumbnail_api.py
fasvadms_client/api/unit_api.py
fasvadms_client/api/vehicle_api.py
fasvadms_client/models/__init__.py
fasvadms_client/models/drive.py
fasvadms_client/models/scene.py
fasvadms_client/models/scene_signal_value.py
fasvadms_client/models/sensor.py
fasvadms_client/models/signal.py
fasvadms_client/models/signal_type.py
fasvadms_client/models/unit.py
fasvadms_client/models/vehicle.py
fasvadms_client-1.1.0.dist-info/METADATA
fasvadms_client-1.1.0.dist-info/RECORD
fasvadms_client-1.1.0.dist-info/WHEEL
fasvadms_client-1.1.0.dist-info/top_level.txt
test/__init__.py
test/test_drive.py
test/test_drive_api.py
test/test_scene.py
test/test_scene_api.py
test/test_scene_signal_value.py
test/test_sensor.py
test/test_sensor_api.py
test/test_signal.py
test/test_signal_api.py
test/test_signal_type.py
test/test_signal_type_api.py
test/test_vehicle.py
test/test_vehicle_api.py
