Metadata-Version: 2.1
Name: fasvadms-client
Version: 1.1.0
Summary: FASva Data Management System Client API
Home-page: UNKNOWN
Author: Lars Klitzke
Author-email: Lars.Klitzke@hs-emden-leer.de
License: UNKNOWN
Keywords: OpenAPI,FASva Data Management System API
Platform: UNKNOWN
Classifier: Operating System :: OS Independent
Classifier: Programming Language :: Python :: 3.5
Classifier: Programming Language :: Python :: 3.6
Classifier: Programming Language :: Python :: 3.7
Classifier: License :: OSI Approved :: GNU Lesser General Public License v3 or later (LGPLv3+)
Classifier: Topic :: Software Development :: Libraries :: Application Frameworks
Classifier: Natural Language :: English
Classifier: Intended Audience :: Developers
Requires-Dist: urllib3 (>=1.15)
Requires-Dist: six (>=1.10)
Requires-Dist: certifi
Requires-Dist: python-dateutil
